alto_exp_bot/__init__.py
alto_exp_bot-0.1.0.dist-info/WHEEL
alto_exp_bot-0.1.0.dist-info/METADATA
alto_exp_bot-0.1.0.dist-info/RECORD
